twist_academic/__init__.py
twist_academic/notify.py
twist_academic-0.1.0.dist-info/LICENSE
twist_academic-0.1.0.dist-info/METADATA
twist_academic-0.1.0.dist-info/WHEEL
twist_academic-0.1.0.dist-info/RECORD
